wireless_sensor_mqtt/__init__.py
wireless_sensor_mqtt/_homeassistant.py
wireless_sensor_mqtt-1.0.0.dist-info/COPYING
wireless_sensor_mqtt-1.0.0.dist-info/METADATA
wireless_sensor_mqtt-1.0.0.dist-info/WHEEL
wireless_sensor_mqtt-1.0.0.dist-info/entry_points.txt
wireless_sensor_mqtt-1.0.0.dist-info/top_level.txt
wireless_sensor_mqtt-1.0.0.dist-info/RECORD
