Metadata-Version: 2.1
Name: wireless-sensor-mqtt
Version: 1.0.0
Summary: MQTT client reporting measurements of FT017TH wireless thermo/hygrometers
Home-page: https://github.com/fphammerle/wireless-sensor-mqtt
Author: Fabian Peter Hammerle
Author-email: fabian@hammerle.me
License: GPLv3+
Project-URL: Changelog, https://github.com/fphammerle/wireless-sensor-mqtt/blob/master/CHANGELOG.md
Keywords: FT017TH,IoT,automation,climate,home-assistant,home-automation,humidity,hygrometer,mqtt,raspberry-pi,sensor,thermometer,wireless
Classifier: Development Status :: 3 - Alpha
Classifier: Intended Audience :: End Users/Desktop
Classifier: Intended Audience :: System Administrators
Classifier: License :: OSI Approved :: GNU General Public License v3 or later (GPLv3+)
Classifier: Operating System :: POSIX :: Linux
Classifier: Programming Language :: Python :: 3.9
Classifier: Programming Language :: Python :: 3.10
Classifier: Programming Language :: Python :: 3.11
Classifier: Topic :: Home Automation
Classifier: Topic :: Utilities
Requires-Python: >=3.9
License-File: COPYING
Requires-Dist: aiomqtt (<3,>=2.3)
Requires-Dist: wireless-sensor (<2,>=1.0.0)
